gradio_imagemeasurement/__init__.py
gradio_imagemeasurement/imagemeasurement.py
gradio_imagemeasurement/imagemeasurement.pyi
gradio_imagemeasurement/templates/component/index.js
gradio_imagemeasurement/templates/component/style.css
gradio_imagemeasurement/templates/example/index.js
gradio_imagemeasurement/templates/example/style.css
gradio_imagemeasurement-0.0.3.dist-info/METADATA
gradio_imagemeasurement-0.0.3.dist-info/WHEEL
gradio_imagemeasurement-0.0.3.dist-info/licenses/LICENSE
gradio_imagemeasurement-0.0.3.dist-info/RECORD
