Metadata-Version: 2.4
Name: gradio_imagemeasurement
Version: 0.0.3
Summary: A component for measuring the distance in pixels between two points in an image.
Project-URL: repository, https://github.com/rybakov-ks/gradio_imagemeasurement
Project-URL: homepage, https://particleanalyzer.ru
Author-email: Kirill Rybakov <rybakov-ks@ya.ru>
License-Expression: GPL-3.0
License-File: LICENSE
Keywords: computer-vision,distance-calculator,gradio-component,gradio-custom-component,gradio-template-Image,image-analysis,image-annotation,image-measurement,image-processing,measurement-tool,pixel-distance,spatial-analysis
Classifier: Development Status :: 3 - Alpha
Classifier: Operating System :: OS Independent
Classifier: Programming Language :: Python :: 3
Classifier: Programming Language :: Python :: 3 :: Only
Classifier: Programming Language :: Python :: 3.8
Classifier: Programming Language :: Python :: 3.9
Classifier: Programming Language :: Python :: 3.10
Classifier: Programming Language :: Python :: 3.11
Classifier: Topic :: Scientific/Engineering
Classifier: Topic :: Scientific/Engineering :: Artificial Intelligence
Classifier: Topic :: Scientific/Engineering :: Visualization
Requires-Python: >=3.10
Requires-Dist: gradio<6.0,>=4.0
Provides-Extra: dev
Requires-Dist: build; extra == 'dev'
Requires-Dist: twine; extra == 'dev'
